kifurushi/__init__.py
kifurushi/abc.py
kifurushi/fields.py
kifurushi/packet.py
kifurushi/utils/__init__.py
kifurushi/utils/network.py
kifurushi/utils/random_values.py
kifurushi-0.6.0.dist-info/LICENSE
kifurushi-0.6.0.dist-info/METADATA
kifurushi-0.6.0.dist-info/WHEEL
kifurushi-0.6.0.dist-info/RECORD
