Metadata-Version: 2.1
Name: kifurushi
Version: 0.6.0
Summary: A simple library to forge network packets
Home-page: https://kifurushi.readthedocs.io/en/stable
License: Apache-2.0
Keywords: kifurushi,networking,protocol,sans-io,packet
Author: lewoudar
Author-email: lewoudar@gmail.com
Requires-Python: >=3.8,<4.0
Classifier: Intended Audience :: Developers
Classifier: License :: OSI Approved :: Apache Software License
Classifier: Operating System :: OS Independent
Classifier: Programming Language :: Python :: 3
Classifier: Programming Language :: Python :: 3.8
Classifier: Programming Language :: Python :: 3.9
Classifier: Programming Language :: Python :: 3.10
Classifier: Programming Language :: Python :: 3.11
Classifier: Programming Language :: Python :: Implementation :: PyPy
Classifier: Topic :: System :: Networking
Requires-Dist: attrs (>=23.1.0,<24.0.0)
Project-URL: Bug Tracker, https://github.com/lewoudar/kifurushi/issues
Project-URL: Documentation, https://kifurushi.readthedocs.io/en/stable
Project-URL: Repository, https://github.com/lewoudar/kifurushi
